MANIFEST.in
setup.py
piui/__init__.py
piui.egg-info/PKG-INFO
piui.egg-info/SOURCES.txt
piui.egg-info/dependency_links.txt
piui.egg-info/requires.txt
piui.egg-info/top_level.txt
piui/static/app.html
piui/static/icon.png
piui/static/jquery-1.9.0.min.js
piui/static/piui.js
piui/static/ratchet.css
piui/static/ratchet.js