Metadata-Version: 1.0
Name: piui
Version: 0.0.9
Summary: Add a mobile UI to your RaspberryPi project.
Home-page: http://github.com/dps/piui
Author: David Singleton
Author-email: davidsingleton@gmail.com
License: BSD
Keywords: raspberrypi mobile ui
Platform: UNKNOWN
Classifier: Development Status :: 3 - Alpha
Classifier: License :: OSI Approved :: BSD License
